asyncio_lifx_scenes/__init__.py
asyncio_lifx_scenes/__main__.py
asyncio_lifx_scenes/cli.py
asyncio_lifx_scenes/models.py
asyncio_lifx_scenes/py.typed
asyncio_lifx_scenes/scenes.py
asyncio_lifx_scenes-0.1.0.dist-info/METADATA
asyncio_lifx_scenes-0.1.0.dist-info/WHEEL
asyncio_lifx_scenes-0.1.0.dist-info/entry_points.txt
asyncio_lifx_scenes-0.1.0.dist-info/licenses/LICENSE
asyncio_lifx_scenes-0.1.0.dist-info/RECORD
