Metadata-Version: 2.4
Name: asyncio-lifx-scenes
Version: 0.1.0
Summary: List and activate scenes via the LIFX Cloud.
Project-URL: Homepage, https://djelibeybi.github.io/asyncio-lifx-scenes/
Project-URL: Repository, https://github.com/djelibeybi/asyncio-lifx-scenes
Project-URL: Documentation, https://djelibeybi.github.io/asyncio-lifx-scenes/
Author-email: Avi Miller <me@dje.li>
License-File: LICENSE
Keywords: python
Classifier: Intended Audience :: Developers
Classifier: Programming Language :: Python
Classifier: Programming Language :: Python :: 3
Classifier: Programming Language :: Python :: 3.9
Classifier: Programming Language :: Python :: 3.10
Classifier: Programming Language :: Python :: 3.11
Classifier: Programming Language :: Python :: 3.12
Classifier: Programming Language :: Python :: 3.13
Classifier: Topic :: Software Development :: Libraries :: Python Modules
Requires-Python: <4.0,>=3.12
Requires-Dist: httpx-auth>=0.23.1
Requires-Dist: httpx>=0.28.1
Requires-Dist: rich>=13.9.4
Requires-Dist: typer>=0.15.1
